easyconnect/__init__.py
easyconnect/db_pool.py
easyconnect/pypyodbc.py
easyconnect/types.py
EasyConnect-1.0.5.dist-info/LICENSE.md
EasyConnect-1.0.5.dist-info/METADATA
EasyConnect-1.0.5.dist-info/WHEEL
EasyConnect-1.0.5.dist-info/top_level.txt
EasyConnect-1.0.5.dist-info/RECORD
